.gitignore
README.md
requirements.txt
setup.py
fec/__init__.py
fec/src/__init__.py
fec/src/data/DataTrining.csv
fec/src/louad_db/__init__.py
fec/src/louad_db/louad_db.py
fec/src/xgboost/Xgboost_model.txt
fec/src/xgboost/__init__.py
fec/src/xgboost/xgboost.py
fecDv.egg-info/PKG-INFO
fecDv.egg-info/SOURCES.txt
fecDv.egg-info/dependency_links.txt
fecDv.egg-info/not-zip-safe
fecDv.egg-info/top_level.txt