Metadata-Version: 2.1
Name: fecDv
Version: 0.0.1
Summary: France energy prediction
Home-page: https://github.com/otmaneelallaki/Frence-Energy-cons
Author: ELALLAKI,David,Sofian
Author-email: otmane.allai1@gmail.com
License: MIT
Platform: UNKNOWN
